{
  "generated_at": "2026-04-26T22:49:33.886738+00:00",
  "version": "1.0",
  "systems": [
    {
      "id": "cci",
      "name": "Crypto Cycle",
      "asset_class": "Crypto",
      "description": "Bitcoin & broader crypto cycle positioning",
      "icon": "₿",
      "color": "#f7931a",
      "dashboard_url": "https://jinhae8971.github.io/crypto-cycle-intelligence/",
      "axis": "x",
      "fetched_at": "2026-04-26T22:49:33.814136+00:00",
      "status": "ok",
      "score": 30.27,
      "subsystem_phase": "Accumulation",
      "phase": "Recovery",
      "phase_emoji": "🌱",
      "phase_color": "#3a8891",
      "dimensions": {
        "valuation": 26.43,
        "onchain": 22.79,
        "sentiment": 28.75,
        "derivatives": null,
        "macro": null,
        "technical": 48.15
      },
      "source_generated_at": "2026-04-26T21:28:21.990790+00:00",
      "stale_hours": 1.35
    },
    {
      "id": "asci",
      "name": "AI / Semiconductor",
      "asset_class": "Equities",
      "description": "AI infrastructure & semiconductor sector cycle",
      "icon": "🤖",
      "color": "#3b82f6",
      "dashboard_url": "https://jinhae8971.github.io/ai-semi-cycle-intelligence/",
      "axis": "y",
      "fetched_at": "2026-04-26T22:49:33.886653+00:00",
      "status": "ok",
      "score": 77.15,
      "subsystem_phase": "Late Bull",
      "phase": "Late Bull",
      "phase_emoji": "🔥",
      "phase_color": "#e76f51",
      "dimensions": {
        "valuation": 56.64,
        "earnings": 82.86,
        "capital": 73.36,
        "sentiment": 85.07,
        "macro": null,
        "technical": 99.58
      },
      "source_generated_at": "2026-04-26T21:36:09.526056+00:00",
      "stale_hours": 1.22
    }
  ],
  "insights": {
    "total_systems": 2,
    "active_systems": 2,
    "avg_score": 53.71,
    "spread": 46.88,
    "extreme_count": 0,
    "narratives": [
      {
        "type": "divergence",
        "title": "Major cross-asset divergence",
        "detail": "AI / Semiconductor (77, Late Bull) vs Crypto Cycle (30, Recovery) — spread 47"
      }
    ]
  }
}